_utils/__init__.py
_utils/_http_client.py
_utils/_video.py
emporiadb-0.1.0.dist-info/licenses/LICENSE
tests/test_import.py
emporiadb-0.1.0.dist-info/METADATA
emporiadb-0.1.0.dist-info/WHEEL
emporiadb-0.1.0.dist-info/top_level.txt
emporiadb-0.1.0.dist-info/RECORD
