Metadata-Version: 2.4
Name: emporiadb
Version: 0.1.0
Summary: Emporiadb Python SDK: Video Database for your AI Applications
Home-page: https://github.com/Emporia-Foundations/emporiadb-python
Author: emporiadb
Author-email: Emporia Foundations <support@emporiadb.io>
License: MIT
Project-URL: Homepage, https://emporiadb.io/
Project-URL: Documentation, https://docs.emporiadb.io
Project-URL: Source, https://github.com/Emporia-Foundations/emporiadb-python
Project-URL: Issues, https://github.com/Emporia-Foundations/emporiadb-python/issues
Classifier: Programming Language :: Python :: 3
Classifier: License :: OSI Approved :: MIT License
Classifier: Operating System :: OS Independent
Requires-Python: >=3.8
License-File: LICENSE
Dynamic: author
Dynamic: home-page
Dynamic: license-file
Dynamic: requires-python
